Metadata-Version: 2.1
Name: auto-tag-rc8
Version: 0.8.2
Summary: Automatically tag a branch based on commit message
Home-page: https://github.com/mateimicu/auto-tag
Author: Matei-Marius Micu
Author-email: contact@mateimicu.com	
License: MIT
Classifier: License :: OSI Approved :: MIT License
Classifier: Programming Language :: Python :: 3
Classifier: Programming Language :: Python :: 3.7
Classifier: Programming Language :: Python :: 3.8
Classifier: Programming Language :: Python :: 3.9
Classifier: Development Status :: 3 - Alpha
Classifier: Environment :: MacOS X
Classifier: Environment :: Console
Classifier: Intended Audience :: Developers
Classifier: Intended Audience :: System Administrators
Classifier: Natural Language :: English
Classifier: Operating System :: MacOS
Classifier: Operating System :: POSIX :: Linux
Classifier: Topic :: Software Development :: Version Control :: Git
Classifier: Topic :: System :: Software Distribution
License-File: LICENSE.md
Requires-Dist: gitpython (>=3.1.18)
Requires-Dist: semantic-version (>=2.8.5)
Requires-Dist: confuse (>=1.5.0)
Requires-Dist: six (>=1.1.0)
